iplotDataAccess/__init__.py
iplotDataAccess/_version.py
iplotDataAccess/appDataAccess.py
iplotDataAccess/csvAccess.py
iplotDataAccess/dataAccess.py
iplotDataAccess/dataCommon.py
iplotDataAccess/dataSource.py
iplotDataAccess/dataSourceConfig.py
iplotDataAccess/data_sources.cfg
iplotDataAccess/imasDBMaster.py
iplotDataAccess/imasUtils.py
iplotDataAccess/imaspyAccess.py
iplotDataAccess/nestedDatatype.py
iplotDataAccess/realTimeStreamer.py
iplotDataAccess/udaAccess.py
iplotDataAccess/dataHandling/exportData/__init__.py
iplotDataAccess/dataHandling/exportData/exportData.py
iplotDataAccess/tests/test_imas.py
iplotDataAccess/tests/test_uda.py
iplotDataAccess/tests/test_zstreamer.py
iplotDataAccess/tests/csv/ITER/MCTB-TEST/data_111.csv
iplotdataaccess-1.3.1.post1.dist-info/METADATA
iplotdataaccess-1.3.1.post1.dist-info/WHEEL
iplotdataaccess-1.3.1.post1.dist-info/top_level.txt
iplotdataaccess-1.3.1.post1.dist-info/RECORD
