Metadata-Version: 2.4
Name: iplotDataAccess
Version: 1.3.1.post1
Summary: Data access for applications using IDSs or CBS
Author-email: ITER Organization <jscabanilla@minsait.com>
Maintainer-email: Jhon Steeven Cabanilla Alvarado <jscabanilla@minsait.com>, Pablo Martin Villares <pmartin@minsait.com>, Mario Gomez Ballesteros <mgomezb@minsait.com>
License: MIT
Project-URL: Homepage, https://github.com/iplot-viz/iplotdataaccess
Project-URL: Repository, https://github.com/iplot-viz/iplotdataaccess.git
Project-URL: Issues, https://github.com/iplot-viz/iplotdataaccess/issues
Keywords: IDS,CBS,Interface Data Structures,Control Breakdown Structure
Classifier: Programming Language :: Python :: 3
Classifier: License :: OSI Approved :: MIT License
Classifier: Operating System :: OS Independent
Requires-Python: >=3.9
Requires-Dist: cachetools>=4.2.0
Requires-Dist: iplotLogging>=1.2.0
Requires-Dist: requests>=2.25.1
Requires-Dist: sseclient-py>=1.7
Requires-Dist: pyarrow>=16.1.0
Requires-Dist: h5py>=3.11.0
Requires-Dist: pandas>=1.2.0
Provides-Extra: imaspy
Requires-Dist: PyYAML>=6.0.1; extra == "imaspy"
Provides-Extra: test
Requires-Dist: pytest>=6.0; extra == "test"
